dash_eidos/DashEidos.py
dash_eidos/Eidos.py
dash_eidos/__init__.py
dash_eidos/_imports_.py
dash_eidos/dash_eidos.min.js
dash_eidos/package-info.json
dash_eidos-0.1.0.dist-info/LICENSE
dash_eidos-0.1.0.dist-info/METADATA
dash_eidos-0.1.0.dist-info/WHEEL
dash_eidos-0.1.0.dist-info/top_level.txt
dash_eidos-0.1.0.dist-info/RECORD
