Metadata-Version: 2.1
Name: dash_eidos
Version: 0.1.0
Summary: Deck.gl component for Dash
Author: Oceanum developers <developers@oceanum.science>
License: MIT
Classifier: Framework :: Dash
License-File: LICENSE
